scs_host/__init__.py
scs_host/client/__init__.py
scs_host/client/mqtt_client.py
scs_host/client/sftp_client.py
scs_host/comms/__init__.py
scs_host/comms/domain_socket.py
scs_host/comms/network_socket.py
scs_host/comms/stdio.py
scs_host/sys/__init__.py
scs_host/sys/host.py
scs_host_posix-3.3.1.dist-info/LICENSE
scs_host_posix-3.3.1.dist-info/METADATA
scs_host_posix-3.3.1.dist-info/WHEEL
scs_host_posix-3.3.1.dist-info/top_level.txt
scs_host_posix-3.3.1.dist-info/RECORD
