Metadata-Version: 2.1
Name: scs-host-posix
Version: 3.3.1
Summary: Host abstractions for data consumers running POSIX-compliant operating systems, including Windows 10.
Home-page: https://github.com/south-coast-science/scs_host_posix
Author: South Coast Science
Author-email: contact@southcoastscience.com
Platform: any
Classifier: Programming Language :: Python :: 3
Classifier: Programming Language :: Python :: 3.8
Classifier: License :: OSI Approved :: MIT License
Classifier: Operating System :: MacOS :: MacOS X
Classifier: Operating System :: Microsoft :: Windows :: Windows 10
Classifier: Operating System :: POSIX
Requires-Python: >3.6
License-File: LICENSE
